prefy/__init__.py
prefy/prefy.py
prefy-1.4.1.dist-info/LICENSE
prefy-1.4.1.dist-info/METADATA
prefy-1.4.1.dist-info/WHEEL
prefy-1.4.1.dist-info/RECORD
