Metadata-Version: 2.3
Name: prefy
Version: 1.4.1
Summary: Streamline the management of your project's preferences through standardized json files.
License: Apache-2.0
Author: pprasquier
Author-email: pprasquier@oncallc.io
Requires-Python: >=3.8,<4.0
Classifier: License :: OSI Approved :: Apache Software License
Classifier: Programming Language :: Python :: 3
Classifier: Programming Language :: Python :: 3.8
Classifier: Programming Language :: Python :: 3.9
Classifier: Programming Language :: Python :: 3.10
Classifier: Programming Language :: Python :: 3.11
Classifier: Programming Language :: Python :: 3.12
Classifier: Programming Language :: Python :: 3.13
Requires-Dist: poetry-dynamic-versioning (>=1.4.0,<2.0.0)
Requires-Dist: setuptools-scm (>=8.1.0,<9.0.0)
